dyntamic/__init__.py
dyntamic/factory.py
dyntamic-0.0.2.dist-info/METADATA
dyntamic-0.0.2.dist-info/WHEEL
dyntamic-0.0.2.dist-info/licenses/LICENSE
dyntamic-0.0.2.dist-info/RECORD
