Metadata-Version: 2.1
Name: dyntamic
Version: 0.0.2
Summary: A light package to generate pydantic models dynamically from JSON Schema
Project-URL: Homepage, https://github.com/c32168/dyntamic
Project-URL: Bug Tracker, https://github.com/c32168/dyntamic/issues
Author-email: RC Max <06102011b@gmail.com>
License-File: LICENSE
Classifier: License :: OSI Approved :: MIT License
Classifier: Operating System :: OS Independent
Classifier: Programming Language :: Python :: 3
Requires-Python: >=3.7
